matplotilib/__init__.py
matplotilib/hello.py
matplotilib-0.4.1.dist-info/METADATA
matplotilib-0.4.1.dist-info/WHEEL
matplotilib-0.4.1.dist-info/entry_points.txt
matplotilib-0.4.1.dist-info/top_level.txt
matplotilib-0.4.1.dist-info/RECORD
